Workbook
Name aporte: App!$D$18
Name montante: App!$D$21
Name patrimonio_acumulado: App!$D$21
Name perfil: App!$C$31
Name periodo: App!$D$19
Name rendimento_carteira: App!$D$14
Name salario: App!$D$13
Name sugestao_investimento: App!$D$15
Name taxa_mensal: App!$D$20

Sheet App
B12: CONFIGURAÇÕES
B13: Salário | D13: 5000
B14: Rendimento Carteira | D14: 0.006
B15: Sugestão de Investimento | D15: =D13*0.3 -> 1500
B17: INVESTIMENTO MENSAL
B18: Quanto investir por mês? | D18: 1500
B19: Por quantos anos? | D19: 5
B20: Taxa de rendimento mensal? | D20: 0.01079
B21: Patrimônio acumulado? | D21: =FV(taxa_mensal,periodo*12,aporte*-1) -> 125665.37
B22: Dividendos mensais? | D22: =montante*rendimento_carteira -> 753.99223
B24: CENÁRIOS | D24: Dividendos
A25: 2 | B25: ="Quanto em "&A25&" anos?" -> Quanto em 2 anos? | C25: =FV($D$20,A25*12,$D$18*-1) -> 40841.441 | D25: =C25*rendimento_carteira -> 245.04865
A26: 5 | B26: ="Quanto em "&A26&" anos?" -> Quanto em 5 anos? | C26: =FV($D$20,A26*12,$D$18*-1) -> 125665.37 | D26: =C26*rendimento_carteira -> 753.99223
A27: 10 | B27: ="Quanto em "&A27&" anos?" -> Quanto em 10 anos? | C27: =FV($D$20,A27*12,$D$18*-1) -> 364926.32 | D27: =C27*rendimento_carteira -> 2189.5579
A28: 20 | B28: ="Quanto em "&A28&" anos?" -> Quanto em 20 anos? | C28: =FV($D$20,A28*12,$D$18*-1) -> 1687797.6 | D28: =C28*rendimento_carteira -> 10126.786
A29: 30 | B29: ="Quanto em "&A29&" anos?" -> Quanto em 30 anos? | C29: =FV($D$20,A29*12,$D$18*-1) -> 6483254.5 | D29: =C29*rendimento_carteira -> 38899.527
B31: PERFIL | C31: AGRESSIVO
B32: VALOR A SER INVESTIDO POR MÊS | C32: =aporte -> 1500
B34: TIPO DE FII | C34: PERCENTUAL SUGERIDO | D34: VALORES
B35: PAPEL | C35: =VLOOKUP(perfil&"-"&App!B35,'Planilha de Apoio'!A1:D19,4,FALSE) -> 0.5 | D35: =$C$32*C35 -> 750
B36: TIJOLO | C36: =VLOOKUP(perfil&"-"&App!B36,'Planilha de Apoio'!A2:D20,4,FALSE) -> 0.1 | D36: =$C$32*C36 -> 150
B37: HÍBRIDO | C37: =VLOOKUP(perfil&"-"&App!B37,'Planilha de Apoio'!A3:D21,4,FALSE) -> 0.05 | D37: =$C$32*C37 -> 75
B38: FOFs | C38: =VLOOKUP(perfil&"-"&App!B38,'Planilha de Apoio'!A4:D22,4,FALSE) -> 0.05 | D38: =$C$32*C38 -> 75
B39: DESENVOLVIMENTO | C39: =VLOOKUP(perfil&"-"&App!B39,'Planilha de Apoio'!A5:D23,4,FALSE) -> 0.2 | D39: =$C$32*C39 -> 300
B40: HOTELARIA | C40: =VLOOKUP(perfil&"-"&App!B40,'Planilha de Apoio'!A6:D24,4,FALSE) -> 0.1 | D40: =$C$32*C40 -> 150
D41: =SUM(D35:D40) -> 1500

Sheet Planilha de Apoio
A1: CHAVE | B1: PERFIL | C1: TIPO DE FII | D1: %
A2: =B2&"-"&C2 -> AGRESSIVO-PAPEL | B2: AGRESSIVO | C2: PAPEL | D2: 0.5
A3: =B3&"-"&C3 -> AGRESSIVO-TIJOLO | B3: AGRESSIVO | C3: TIJOLO | D3: 0.1
A4: =B4&"-"&C4 -> AGRESSIVO-HÍBRIDO | B4: AGRESSIVO | C4: HÍBRIDO | D4: 0.05
A5: =B5&"-"&C5 -> AGRESSIVO-FOFs | B5: AGRESSIVO | C5: FOFs | D5: 0.05
A6: =B6&"-"&C6 -> AGRESSIVO-DESENVOLVIMENTO | B6: AGRESSIVO | C6: DESENVOLVIMENTO | D6: 0.2
A7: =B7&"-"&C7 -> AGRESSIVO-HOTELARIA | B7: AGRESSIVO | C7: HOTELARIA | D7: 0.1
A8: =B8&"-"&C8 -> MODERADO-PAPEL | B8: MODERADO | C8: PAPEL | D8: 0.32
A9: =B9&"-"&C9 -> MODERADO-TIJOLO | B9: MODERADO | C9: TIJOLO | D9: 0.4
A10: =B10&"-"&C10 -> MODERADO-HÍBRIDO | B10: MODERADO | C10: HÍBRIDO | D10: 0.08
A11: =B11&"-"&C11 -> MODERADO-FOFs | B11: MODERADO | C11: FOFs | D11: 0.1
A12: =B12&"-"&C12 -> MODERADO-DESENVOLVIMENTO | B12: MODERADO | C12: DESENVOLVIMENTO | D12: 0.1
A13: =B13&"-"&C13 -> MODERADO-HOTELARIA | B13: MODERADO | C13: HOTELARIA | D13: 0.1
... A19: =B19&"-"&C19 -> CONSERVADOR-HOTELARIA | B19: CONSERVADOR | C19: HOTELARIA | D19: 0
